LICENSE
README.md
setup.py
nonebot_plugin_watermarker/__init__.py
nonebot_plugin_watermarker/config.py
nonebot_plugin_watermarker/fuctions.py
nonebot_plugin_watermarker.egg-info/PKG-INFO
nonebot_plugin_watermarker.egg-info/SOURCES.txt
nonebot_plugin_watermarker.egg-info/dependency_links.txt
nonebot_plugin_watermarker.egg-info/requires.txt
nonebot_plugin_watermarker.egg-info/top_level.txt