Metadata-Version: 2.1
Name: nonebot-plugin-watermarker
Version: 0.2.0
Summary: 为nonebot机器人发送的图片加上水印
Home-page: https://github.com/X-Skirt-X/nonebot-plugin-watermarker
Author: XU
Author-email: Woyerpa@outlook.com
License: MIT License
Platform: UNKNOWN
License-File: LICENSE
